{"test":{"sharpe":1.51,"years":7.6,"skew":0.03,"kurtosis":13.9,"nonnormality_correction":1.013,"psr_vs_0":1.0,"psr_vs_0.5":0.997,"psr_vs_1.0":0.9182,"min_years_for_95pct_vs_0":1.2},"selection":{"n_trials":60,"best_train_sharpe":0.47,"sd_sharpe_across_trials":0.404,"expected_max_sharpe_null":0.95,"dsr":0.0586,"train_years":11.0,"min_years_for_95pct_dsr":null,"v1_comparison":{"n_trials":1500,"dsr":0.692,"min_years":79.6,"note":"v1 swept 1,500 combos over the full sample; its winner was statistically indistinguishable from lucky selection."}}}